assembling/__init__.py
assembling/dataset_assembler.py
assembling/dataset_cache.py
assembling/dataset_labeler_abstract.py
assembling/dataset_timeframe_aggregator.py
assembling/volatility_dataset_labeler.py
common/__init__.py
common/common.py
indicators/__init__.py
indicators/indicator_abstract.py
indicators/indicator_interface.py
indicators/ma_indicator.py
loader/__init__.py
loader/book_dept_loader_interface.py
loader/ohlc_loader_interface.py
loader/trades_loader_interface.py
loader/binance_vision/__init__.py
loader/binance_vision/book_depth_loader.py
loader/binance_vision/ohlc_loader.py
loader/binance_vision/trades_loader.py
loader/polygon/__init__.py
loader/polygon/ohlc_loader.py
loader/polygon/trades_loader.py
providers/__init__.py
providers/crypto_series_data_provider.py
providers/stock_series_data_provider.py
tests/__init__.py
tests/test_dataset_timeframe_aggregator.py
market_data_provider-0.4.0.dist-info/METADATA
market_data_provider-0.4.0.dist-info/WHEEL
market_data_provider-0.4.0.dist-info/top_level.txt
market_data_provider-0.4.0.dist-info/RECORD
