Metadata-Version: 2.1
Name: market-data-provider
Version: 0.4.0
Summary: Market data provider
Author: Maksym Usanin (usanin.max@gmail.com)
Classifier: Programming Language :: Python :: 3
Classifier: Programming Language :: Python :: 3.11
Classifier: Operating System :: OS Independent
Requires-Python: >=3.11
Requires-Dist: requests
Requires-Dist: tenacity
Requires-Dist: pytz
